odoo/addons/sale_invoicing_date_from_picking/README.rst
odoo/addons/sale_invoicing_date_from_picking/__init__.py
odoo/addons/sale_invoicing_date_from_picking/__manifest__.py
odoo/addons/sale_invoicing_date_from_picking/i18n/it.po
odoo/addons/sale_invoicing_date_from_picking/i18n/sale_invoicing_date_from_picking.pot
odoo/addons/sale_invoicing_date_from_picking/readme/CONTRIBUTORS.md
odoo/addons/sale_invoicing_date_from_picking/readme/DESCRIPTION.md
odoo/addons/sale_invoicing_date_from_picking/readme/USAGE.md
odoo/addons/sale_invoicing_date_from_picking/static/description/icon.png
odoo/addons/sale_invoicing_date_from_picking/static/description/index.html
odoo/addons/sale_invoicing_date_from_picking/tests/__init__.py
odoo/addons/sale_invoicing_date_from_picking/tests/test_sale_invoicing_date_from_picking.py
odoo/addons/sale_invoicing_date_from_picking/wizard/__init__.py
odoo/addons/sale_invoicing_date_from_picking/wizard/sale_advance_payment_inv.py
odoo_addon_sale_invoicing_date_from_picking-16.0.1.0.0.4.dist-info/METADATA
odoo_addon_sale_invoicing_date_from_picking-16.0.1.0.0.4.dist-info/WHEEL
odoo_addon_sale_invoicing_date_from_picking-16.0.1.0.0.4.dist-info/top_level.txt
odoo_addon_sale_invoicing_date_from_picking-16.0.1.0.0.4.dist-info/RECORD
