Metadata-Version: 2.1
Name: odoo-addon-sale_invoicing_date_from_picking
Version: 16.0.1.0.0.4
Summary: Applies the wizard date to invoices generated from pickings
Home-page: https://github.com/OCA/account-invoicing
Author: Sygel, Odoo Community Association (OCA)
Author-email: support@odoo-community.org
License: AGPL-3
Classifier: Programming Language :: Python
Classifier: Framework :: Odoo
Classifier: Framework :: Odoo :: 16.0
Classifier: License :: OSI Approved :: GNU Affero General Public License v3
Requires-Python: >=3.10
Requires-Dist: odoo-addon-sale-invoicing-date-selection<16.1dev,>=16.0dev
Requires-Dist: odoo-addon-sale-order-invoicing-picking-filter<16.1dev,>=16.0dev
Requires-Dist: odoo<16.1dev,>=16.0a
